[
  {
    "clientKey": "Renoir Design",
    "numero": "F001",
    "status": "unpaid",
    "description": "Site vitrine 3 pages",
    "montant": 800,
    "date": "2024-01-20"
  },
  {
    "clientKey": "Renoir Design",
    "numero": "F002",
    "status": "paid",
    "description": "Logo vectoriel",
    "montant": 300,
    "date": "2024-02-05"
  },
  {
    "clientKey": "Renoir Design",
    "numero": "F003",
    "status": "unpaid",
    "description": "Charte graphique",
    "montant": 600,
    "date": "2024-03-10"
  },
  {
    "clientKey": "Renoir Design",
    "numero": "F004",
    "status": "paid",
    "description": "Carte de visite imprimée",
    "montant": 150,
    "date": "2024-03-20"
  },
  {
    "clientKey": "MJ Architecture",
    "numero": "F2025-045",
    "status": "paid",
    "description": "Consultation chantier - Projet Rivoli",
    "montant": 950,
    "date": "2025-06-05"
  },
  {
    "clientKey": "MJ Architecture",
    "numero": "F2025-052",
    "status": "unpaid",
    "description": "Plans de rénovation – Appartement Voltaire",
    "montant": 1400,
    "date": "2025-06-15"
  },
  {
    "clientKey": "MJ Architecture",
    "numero": "F2025-060",
    "status": "paid",
    "description": "Mission express – Vérification conformité permis",
    "montant": 550,
    "date": "2025-06-25"
  }
]
